{
  "filename": "siamese_spatial_dropout",
  "dataset": "hotspot",
  "augment": false,
  "siamese": true,
  "rev_comp": false,
  "dropout": false,
  "mc_dropout": false,
  "spatial_dropout": true,
  "rc_spatial_dropout": true,
  "activation": "relu",
  "dropout_rate": 0.2,
  "num_conv": 3,
  "filters": 12,
  "kernel_size": 14,
  "pool_size": 40,
  "pooling": "max",
  "num_epochs": 100,
  "patience": 60,
  "seed_num": 3000,
  "strides": 40,
  "units": 2,
  "correlation": 0,
  "acc": 0.6226541554959786
}